<?xml version="1.0" encoding="utf-8" ?><dwsync><file name="TG_Date.js" server="64.64.8.234//var/www/vhosts/" local="3451635944" remote="1997233033879190535" /><file name="TG_Mapping.js" server="64.64.8.234//var/www/vhosts/" local="3450801827" remote="1997233033879190535" /><file name="TG_Mediator.js" server="64.64.8.234//var/www/vhosts/" local="3450801827" remote="1997233033879190536" /><file name="TG_Org.js" server="64.64.8.234//var/www/vhosts/" local="3456845156" remote="1997233033879190537" /><file name="TG_Timeline.js" server="64.64.8.234//var/www/vhosts/" local="3450801827" remote="1997233033879190537" /><file name="TG_TimelineView.js" server="64.64.8.234//var/www/vhosts/" local="3456854119" remote="1997233033879190539" /><file name="TG_TimelineViewListTest.js" server="64.64.8.234//var/www/vhosts/" local="3456845646" remote="1997233033879190541" /><file name="Timeglider.css" server="64.64.8.234//var/www/vhosts/" local="3456859071" remote="1997233033879190542" /><file name="timeglider.datepicker.css" server="64.64.8.234//var/www/vhosts/" local="3451637699" remote="1997233033879190543" /><file name="timeglider.datepicker.js" server="64.64.8.234//var/www/vhosts/" local="3455022847" remote="1997233033879190543" /><file name="timeglider.timeline.widget.js" server="64.64.8.234//var/www/vhosts/" local="3450807041" remote="1997233033879190544" /><file name="Timeglider_mobile.css" server="64.64.8.234//var/www/vhosts/" local="3456845301" remote="1997233033879190544" /></dwsync>